package/__init__.py
package/main.py
telegram_api_robot-1.0.0.dist-info/METADATA
telegram_api_robot-1.0.0.dist-info/WHEEL
telegram_api_robot-1.0.0.dist-info/top_level.txt
telegram_api_robot-1.0.0.dist-info/RECORD
