Metadata-Version: 2.1
Name: telegram-api-robot
Version: 1.0.0
Summary: UNKNOWN
Home-page: UNKNOWN
Author: mr nick and missis name
License: UNKNOWN
Platform: UNKNOWN
Requires-Python: >=3.7
Requires-Dist: requests (>=2.25.1)
